gcloud_flask_oauth_cors/__init__.py
gcloud_flask_oauth_cors/auth.py
gcloud_flask_oauth_cors-0.1.1.dist-info/LICENSE
gcloud_flask_oauth_cors-0.1.1.dist-info/METADATA
gcloud_flask_oauth_cors-0.1.1.dist-info/WHEEL
gcloud_flask_oauth_cors-0.1.1.dist-info/top_level.txt
gcloud_flask_oauth_cors-0.1.1.dist-info/RECORD
