Metadata-Version: 2.1
Name: gcloud-flask-oauth-cors
Version: 0.1.1
Summary: A tiny utility to authenticate requests using GCP OAuth and send CORS headers in Flask
Home-page: https://github.com/googlecloudplatform/flask-oauth-cors
Author: Jez Humble
Author-email: humble@google.com
License: UNKNOWN
Platform: UNKNOWN
Classifier: Programming Language :: Python :: 3
Classifier: License :: OSI Approved :: Apache Software License
Classifier: Operating System :: OS Independent
Requires-Dist: google-api-python-client
Requires-Dist: google-auth
